lofti_gaiaDR2/__init__.py
lofti_gaiaDR2/lofti.py
lofti_gaiaDR2/loftitools.py
lofti_gaiaDR2/test.py
lofti_gaiaDR2-1.1.3.dist-info/LICENSE
lofti_gaiaDR2-1.1.3.dist-info/METADATA
lofti_gaiaDR2-1.1.3.dist-info/WHEEL
lofti_gaiaDR2-1.1.3.dist-info/top_level.txt
lofti_gaiaDR2-1.1.3.dist-info/RECORD
