Metadata-Version: 2.1
Name: lofti-gaiaDR2
Version: 1.1.3
Summary: Orbit fitting with Gaia astrometry
Home-page: https://github.com/logan-pearce/lofti_gaiaDR2
Author: Logan Pearce
Author-email: loganpearce1@email.arizona.edu
License: MIT
Download-URL: https://github.com/logan-pearce/lofti_gaiaDR2/archive/1.1.2.tar.gz
Platform: UNKNOWN
Requires-Dist: numpy
Requires-Dist: matplotlib
Requires-Dist: astropy (>=4.0.1.post1)
Requires-Dist: astroquery (>=0.4)
